pyfunctionhood/__init__.py
pyfunctionhood/clause.py
pyfunctionhood/function.py
pyfunctionhood/hassediagram.py
pyfunctionhood/main.py
pyfunctionhood/powerset.py
pyfunctionhood-0.1.2.dist-info/licenses/LICENSE
pyfunctionhood-0.1.2.dist-info/METADATA
pyfunctionhood-0.1.2.dist-info/WHEEL
pyfunctionhood-0.1.2.dist-info/entry_points.txt
pyfunctionhood-0.1.2.dist-info/top_level.txt
pyfunctionhood-0.1.2.dist-info/RECORD
