Metadata-Version: 2.4
Name: pyfunctionhood
Version: 0.1.2
Summary: Local computation of immediate neighbours of a given monotone non-degenerate Boolean function
Author: Patrícia Roxo, José E. R. Cury, Vasco Manquinho, Claudine Chaouiya
Author-email: "Pedro T. Monteiro" <Pedro.Tiago.Monteiro@tecnico.ulisboa.pt>
License: AGPL-3.0
Project-URL: Homepage, https://github.com/ptgm/pyfunctionhood
Project-URL: Repository, https://github.com/ptgm/pyfunctionhood
Keywords: boolean,monotone,hasse-diagram,functions,bitarray
Classifier: Programming Language :: Python
Classifier: Programming Language :: Python :: 3
Classifier: Programming Language :: Python :: 3.9
Classifier: Programming Language :: Python :: 3.10
Classifier: Programming Language :: Python :: 3.11
Classifier: Programming Language :: Python :: 3.12
Classifier: Programming Language :: Python :: 3.13
Classifier: Operating System :: OS Independent
Classifier: License :: OSI Approved :: GNU Affero General Public License v3
Classifier: Intended Audience :: Science/Research
Classifier: Topic :: Scientific/Engineering :: Mathematics
Requires-Python: >=3.9
License-File: LICENSE
Requires-Dist: bitarray
Dynamic: license-file
